django_pdf_generator-0.1.3.dist-info/DESCRIPTION.rst
django_pdf_generator-0.1.3.dist-info/METADATA
django_pdf_generator-0.1.3.dist-info/RECORD
django_pdf_generator-0.1.3.dist-info/WHEEL
django_pdf_generator-0.1.3.dist-info/metadata.json
django_pdf_generator-0.1.3.dist-info/top_level.txt
pdf_generator/__init__.py
pdf_generator/admin.py
pdf_generator/apps.py
pdf_generator/generators.py
pdf_generator/models.py
pdf_generator/rasterize.js
pdf_generator/renderers.py
pdf_generator/settings.py
pdf_generator/tests.py
pdf_generator/urls.py
pdf_generator/utils.py
pdf_generator/views.py
pdf_generator/migrations/__init__.py
pdf_generator/temp/empty.txt
pdf_generator/templates/pdf_generator/empty.txt
