Metadata-Version: 2.0
Name: django-pdf-generator
Version: 0.1.3
Summary: Generate PDF from HTML with django
Home-page: https://github.com/charlesthk/django-pdf-generator
Author: Charles TISSIER
Author-email: charles@vingtcinq.io
License: MIT
Keywords: python django pdf html phantomjs
Platform: UNKNOWN
Classifier: Development Status :: 5 - Production/Stable
Classifier: Intended Audience :: Developers
Classifier: Topic :: Software Development :: Libraries :: Python Modules
Classifier: License :: OSI Approved :: MIT License
Classifier: Framework :: Django :: 1.10
Classifier: Framework :: Django :: 1.9
Classifier: Programming Language :: Python :: 2
Classifier: Programming Language :: Python :: 2.3
Classifier: Programming Language :: Python :: 2.4
Classifier: Programming Language :: Python :: 2.5
Classifier: Programming Language :: Python :: 2.6
Classifier: Programming Language :: Python :: 2.7
